[
  {
    "id": "4201646672",
    "type": "WatchEvent",
    "actor": {
      "id": 4921183,
      "login": "kamranahmedse",
      "display_login": "kamranahmedse",
      "gravatar_id": "",
      "url": "https://api.github.com/users/kamranahmedse",
      "avatar_url": "https://avatars.githubusercontent.com/u/4921183?"
    },
    "repo": {
      "id": 692174763,
      "name": "Obra-Studio/obra-icons-mr",
      "url": "https://api.github.com/repos/Obra-Studio/obra-icons-mr"
    },
    "payload": {
      "action": "started"
    },
    "public": true,
    "created_at": "2025-10-23T02:10:00Z",
    "org": {
      "id": 145154303,
      "login": "Obra-Studio",
      "gravatar_id": "",
      "url": "https://api.github.com/orgs/Obra-Studio",
      "avatar_url": "https://avatars.githubusercontent.com/u/145154303?"
    }
  },
  {
    "id": "5375856693",
    "type": "PushEvent",
    "actor": {
      "id": 4921183,
      "login": "kamranahmedse",
      "display_login": "kamranahmedse",
      "gravatar_id": "",
      "url": "https://api.github.com/users/kamranahmedse",
      "avatar_url": "https://avatars.githubusercontent.com/u/4921183?"
    },
    "repo": {
      "id": 85077558,
      "name": "kamranahmedse/developer-roadmap",
      "url": "https://api.github.com/repos/kamranahmedse/developer-roadmap"
    },
    "payload": {
      "repository_id": 85077558,
      "push_id": 27665828802,
      "ref": "refs/heads/master",
      "head": "36f20b31f4f4f183c52eb2580eaf4ca8b873b3a5",
      "before": "0d0060c98d08e6624fcc12427f6c476c564d9a34"
    },
    "public": true,
    "created_at": "2025-10-22T05:39:20Z"
  },
  {
    "id": "4162238770",
    "type": "IssuesEvent",
    "actor": {
      "id": 4921183,
      "login": "kamranahmedse",
      "display_login": "kamranahmedse",
      "gravatar_id": "",
      "url": "https://api.github.com/users/kamranahmedse",
      "avatar_url": "https://avatars.githubusercontent.com/u/4921183?"
    },
    "repo": {
      "id": 85077558,
      "name": "kamranahmedse/developer-roadmap",
      "url": "https://api.github.com/repos/kamranahmedse/developer-roadmap"
    },
    "payload": {
      "action": "closed",
      "issue": {
        "url": "https://api.github.com/repos/kamranahmedse/developer-roadmap/issues/9218",
        "repository_url": "https://api.github.com/repos/kamranahmedse/developer-roadmap",
        "labels_url": "https://api.github.com/repos/kamranahmedse/developer-roadmap/issues/9218/labels{/name}",
        "comments_url": "https://api.github.com/repos/kamranahmedse/developer-roadmap/issues/9218/comments",
        "events_url": "https://api.github.com/repos/kamranahmedse/developer-roadmap/issues/9218/events",
        "html_url": "https://github.com/kamranahmedse/developer-roadmap/issues/9218",
        "id": 3483388343,
        "node_id": "I_kwDOBRIuNs7PoEm3",
        "number": 9218,
        "title": "bug: AI quiz, invalid checks - correct answer marked as invalid",
        "user": {
          "login": "devzom",
          "id": 1417473,
          "node_id": "MDQ6VXNlcjE0MTc0NzM=",
          "avatar_url": "https://avatars.githubusercontent.com/u/1417473?v=4",
          "gravatar_id": "",
          "url": "https://api.github.com/users/devzom",
          "html_url": "https://github.com/devzom",
          "followers_url": "https://api.github.com/users/devzom/followers",
          "following_url": "https://api.github.com/users/devzom/following{/other_user}",
          "gists_url": "https://api.github.com/users/devzom/gists{/gist_id}",
          "starred_url": "https://api.github.com/users/devzom/starred{/owner}{/repo}",
          "subscriptions_url": "https://api.github.com/users/devzom/subscriptions",
          "organizations_url": "https://api.github.com/users/devzom/orgs",
          "repos_url": "https://api.github.com/users/devzom/repos",
          "events_url": "https://api.github.com/users/devzom/events{/privacy}",
          "received_events_url": "https://api.github.com/users/devzom/received_events",
          "type": "User",
          "user_view_type": "public",
          "site_admin": false
        },
        "labels": [
          {
            "id": 561371921,
            "node_id": "MDU6TGFiZWw1NjEzNzE5MjE=",
            "url": "https://api.github.com/repos/kamranahmedse/developer-roadmap/labels/bug",
            "name": "bug",
            "color": "ee0701",
            "default": true,
            "description": "Indicates an unexpected problem or unintended behavior"
          }
        ],
        "state": "closed",
        "locked": false,
        "assignee": null,
        "assignees": [

        ],
        "milestone": null,
        "comments": 1,
        "created_at": "2025-10-04T08:11:39Z",
        "updated_at": "2025-10-21T12:48:56Z",
        "closed_at": "2025-10-21T12:48:56Z",
        "active_lock_reason": null,
        "sub_issues_summary": {
          "total": 0,
          "completed": 0,
          "percent_completed": 0
        },
        "issue_dependencies_summary": {
          "blocked_by": 0,
          "total_blocked_by": 0,
          "blocking": 0,
          "total_blocking": 0
        },
        "body": "### What is the URL where the issue is happening\n\nhttps://roadmap.sh/ai/quiz/javascript-fundamentals-quiz-1759565276780\n\n### What browsers are you seeing the problem on?\n\nChrome\n\n### Describe the Bug\n\nIt appear that generated AI quiz miss the correct context and detect questions as incorrectly, when they're not incorrect.\n\n<img width=\"1966\" height=\"957\" alt=\"Image\" src=\"https://github.com/user-attachments/assets/ca38734e-3a37-42c2-b99f-ea2c24091552\" />\n\n> Incorrect Answer\n> The typeof operator in JavaScript is used to determine the data type of a variable. It returns a string indicating the type of the operand. For example, typeof 42 returns \"number\", and typeof \"hello\" returns \"string\".\n\nthat's not right\n\n### Output from browser console (if any)\n\n_No response_\n\n### Participation\n\n- [ ] I am willing to submit a pull request for this issue.",
        "reactions": {
          "url": "https://api.github.com/repos/kamranahmedse/developer-roadmap/issues/9218/reactions",
          "total_count": 1,
          "+1": 0,
          "-1": 0,
          "laugh": 0,
          "hooray": 0,
          "confused": 0,
          "heart": 0,
          "rocket": 1,
          "eyes": 0
        },
        "timeline_url": "https://api.github.com/repos/kamranahmedse/developer-roadmap/issues/9218/timeline",
        "performed_via_github_app": null,
        "state_reason": "completed"
      }
    },
    "public": true,
    "created_at": "2025-10-21T12:48:59Z"
  },
  {
    "id": "4162237808",
    "type": "IssueCommentEvent",
    "actor": {
      "id": 4921183,
      "login": "kamranahmedse",
      "display_login": "kamranahmedse",
      "gravatar_id": "",
      "url": "https://api.github.com/users/kamranahmedse",
      "avatar_url": "https://avatars.githubusercontent.com/u/4921183?"
    },
    "repo": {
      "id": 85077558,
      "name": "kamranahmedse/developer-roadmap",
      "url": "https://api.github.com/repos/kamranahmedse/developer-roadmap"
    },
    "payload": {
      "action": "created",
      "issue": {
        "url": "https://api.github.com/repos/kamranahmedse/developer-roadmap/issues/9218",
        "repository_url": "https://api.github.com/repos/kamranahmedse/developer-roadmap",
        "labels_url": "https://api.github.com/repos/kamranahmedse/developer-roadmap/issues/9218/labels{/name}",
        "comments_url": "https://api.github.com/repos/kamranahmedse/developer-roadmap/issues/9218/comments",
        "events_url": "https://api.github.com/repos/kamranahmedse/developer-roadmap/issues/9218/events",
        "html_url": "https://github.com/kamranahmedse/developer-roadmap/issues/9218",
        "id": 3483388343,
        "node_id": "I_kwDOBRIuNs7PoEm3",
        "number": 9218,
        "title": "bug: AI quiz, invalid checks - correct answer marked as invalid",
        "user": {
          "login": "devzom",
          "id": 1417473,
          "node_id": "MDQ6VXNlcjE0MTc0NzM=",
          "avatar_url": "https://avatars.githubusercontent.com/u/1417473?v=4",
          "gravatar_id": "",
          "url": "https://api.github.com/users/devzom",
          "html_url": "https://github.com/devzom",
          "followers_url": "https://api.github.com/users/devzom/followers",
          "following_url": "https://api.github.com/users/devzom/following{/other_user}",
          "gists_url": "https://api.github.com/users/devzom/gists{/gist_id}",
          "starred_url": "https://api.github.com/users/devzom/starred{/owner}{/repo}",
          "subscriptions_url": "https://api.github.com/users/devzom/subscriptions",
          "organizations_url": "https://api.github.com/users/devzom/orgs",
          "repos_url": "https://api.github.com/users/devzom/repos",
          "events_url": "https://api.github.com/users/devzom/events{/privacy}",
          "received_events_url": "https://api.github.com/users/devzom/received_events",
          "type": "User",
          "user_view_type": "public",
          "site_admin": false
        },
        "labels": [
          {
            "id": 561371921,
            "node_id": "MDU6TGFiZWw1NjEzNzE5MjE=",
            "url": "https://api.github.com/repos/kamranahmedse/developer-roadmap/labels/bug",
            "name": "bug",
            "color": "ee0701",
            "default": true,
            "description": "Indicates an unexpected problem or unintended behavior"
          }
        ],
        "state": "closed",
        "locked": false,
        "assignee": null,
        "assignees": [

        ],
        "milestone": null,
        "comments": 1,
        "created_at": "2025-10-04T08:11:39Z",
        "updated_at": "2025-10-21T12:48:56Z",
        "closed_at": "2025-10-21T12:48:56Z",
        "active_lock_reason": null,
        "sub_issues_summary": {
          "total": 0,
          "completed": 0,
          "percent_completed": 0
        },
        "issue_dependencies_summary": {
          "blocked_by": 0,
          "total_blocked_by": 0,
          "blocking": 0,
          "total_blocking": 0
        },
        "body": "### What is the URL where the issue is happening\n\nhttps://roadmap.sh/ai/quiz/javascript-fundamentals-quiz-1759565276780\n\n### What browsers are you seeing the problem on?\n\nChrome\n\n### Describe the Bug\n\nIt appear that generated AI quiz miss the correct context and detect questions as incorrectly, when they're not incorrect.\n\n<img width=\"1966\" height=\"957\" alt=\"Image\" src=\"https://github.com/user-attachments/assets/ca38734e-3a37-42c2-b99f-ea2c24091552\" />\n\n> Incorrect Answer\n> The typeof operator in JavaScript is used to determine the data type of a variable. It returns a string indicating the type of the operand. For example, typeof 42 returns \"number\", and typeof \"hello\" returns \"string\".\n\nthat's not right\n\n### Output from browser console (if any)\n\n_No response_\n\n### Participation\n\n- [ ] I am willing to submit a pull request for this issue.",
        "reactions": {
          "url": "https://api.github.com/repos/kamranahmedse/developer-roadmap/issues/9218/reactions",
          "total_count": 1,
          "+1": 0,
          "-1": 0,
          "laugh": 0,
          "hooray": 0,
          "confused": 0,
          "heart": 0,
          "rocket": 1,
          "eyes": 0
        },
        "timeline_url": "https://api.github.com/repos/kamranahmedse/developer-roadmap/issues/9218/timeline",
        "performed_via_github_app": null,
        "state_reason": "completed"
      },
      "comment": {
        "url": "https://api.github.com/repos/kamranahmedse/developer-roadmap/issues/comments/3426443653",
        "html_url": "https://github.com/kamranahmedse/developer-roadmap/issues/9218#issuecomment-3426443653",
        "issue_url": "https://api.github.com/repos/kamranahmedse/developer-roadmap/issues/9218",
        "id": 3426443653,
        "node_id": "IC_kwDOBRIuNs7MO2GF",
        "user": {
          "login": "kamranahmedse",
          "id": 4921183,
          "node_id": "MDQ6VXNlcjQ5MjExODM=",
          "avatar_url": "https://avatars.githubusercontent.com/u/4921183?v=4",
          "gravatar_id": "",
          "url": "https://api.github.com/users/kamranahmedse",
          "html_url": "https://github.com/kamranahmedse",
          "followers_url": "https://api.github.com/users/kamranahmedse/followers",
          "following_url": "https://api.github.com/users/kamranahmedse/following{/other_user}",
          "gists_url": "https://api.github.com/users/kamranahmedse/gists{/gist_id}",
          "starred_url": "https://api.github.com/users/kamranahmedse/starred{/owner}{/repo}",
          "subscriptions_url": "https://api.github.com/users/kamranahmedse/subscriptions",
          "organizations_url": "https://api.github.com/users/kamranahmedse/orgs",
          "repos_url": "https://api.github.com/users/kamranahmedse/repos",
          "events_url": "https://api.github.com/users/kamranahmedse/events{/privacy}",
          "received_events_url": "https://api.github.com/users/kamranahmedse/received_events",
          "type": "User",
          "user_view_type": "public",
          "site_admin": false
        },
        "created_at": "2025-10-21T12:48:56Z",
        "updated_at": "2025-10-21T12:48:56Z",
        "body": "Thank you for reporting, this should be fixed now.",
        "reactions": {
          "url": "https://api.github.com/repos/kamranahmedse/developer-roadmap/issues/comments/3426443653/reactions",
          "total_count": 1,
          "+1": 0,
          "-1": 0,
          "laugh": 0,
          "hooray": 1,
          "confused": 0,
          "heart": 0,
          "rocket": 0,
          "eyes": 0
        },
        "performed_via_github_app": null
      }
    },
    "public": true,
    "created_at": "2025-10-21T12:48:56Z"
  },
  {
    "id": "5354204829",
    "type": "PushEvent",
    "actor": {
      "id": 4921183,
      "login": "kamranahmedse",
      "display_login": "kamranahmedse",
      "gravatar_id": "",
      "url": "https://api.github.com/users/kamranahmedse",
      "avatar_url": "https://avatars.githubusercontent.com/u/4921183?"
    },
    "repo": {
      "id": 85077558,
      "name": "kamranahmedse/developer-roadmap",
      "url": "https://api.github.com/repos/kamranahmedse/developer-roadmap"
    },
    "payload": {
      "repository_id": 85077558,
      "push_id": 27644114217,
      "ref": "refs/heads/master",
      "head": "0d0060c98d08e6624fcc12427f6c476c564d9a34",
      "before": "1a83102edd3539b572e97222114aae80452830ed"
    },
    "public": true,
    "created_at": "2025-10-21T10:29:19Z"
  },
  {
    "id": "4158125183",
    "type": "IssuesEvent",
    "actor": {
      "id": 4921183,
      "login": "kamranahmedse",
      "display_login": "kamranahmedse",
      "gravatar_id": "",
      "url": "https://api.github.com/users/kamranahmedse",
      "avatar_url": "https://avatars.githubusercontent.com/u/4921183?"
    },
    "repo": {
      "id": 85077558,
      "name": "kamranahmedse/developer-roadmap",
      "url": "https://api.github.com/repos/kamranahmedse/developer-roadmap"
    },
    "payload": {
      "action": "closed",
      "issue": {
        "url": "https://api.github.com/repos/kamranahmedse/developer-roadmap/issues/9199",
        "repository_url": "https://api.github.com/repos/kamranahmedse/developer-roadmap",
        "labels_url": "https://api.github.com/repos/kamranahmedse/developer-roadmap/issues/9199/labels{/name}",
        "comments_url": "https://api.github.com/repos/kamranahmedse/developer-roadmap/issues/9199/comments",
        "events_url": "https://api.github.com/repos/kamranahmedse/developer-roadmap/issues/9199/events",
        "html_url": "https://github.com/kamranahmedse/developer-roadmap/issues/9199",
        "id": 3467372293,
        "node_id": "I_kwDOBRIuNs7Oq-cF",
        "number": 9199,
        "title": "Biome section missing content",
        "user": {
          "login": "TohDeKai",
          "id": 66544431,
          "node_id": "MDQ6VXNlcjY2NTQ0NDMx",
          "avatar_url": "https://avatars.githubusercontent.com/u/66544431?v=4",
          "gravatar_id": "",
          "url": "https://api.github.com/users/TohDeKai",
          "html_url": "https://github.com/TohDeKai",
          "followers_url": "https://api.github.com/users/TohDeKai/followers",
          "following_url": "https://api.github.com/users/TohDeKai/following{/other_user}",
          "gists_url": "https://api.github.com/users/TohDeKai/gists{/gist_id}",
          "starred_url": "https://api.github.com/users/TohDeKai/starred{/owner}{/repo}",
          "subscriptions_url": "https://api.github.com/users/TohDeKai/subscriptions",
          "organizations_url": "https://api.github.com/users/TohDeKai/orgs",
          "repos_url": "https://api.github.com/users/TohDeKai/repos",
          "events_url": "https://api.github.com/users/TohDeKai/events{/privacy}",
          "received_events_url": "https://api.github.com/users/TohDeKai/received_events",
          "type": "User",
          "user_view_type": "public",
          "site_admin": false
        },
        "labels": [
          {
            "id": 6934955806,
            "node_id": "LA_kwDOBRIuNs8AAAABnVsHHg",
            "url": "https://api.github.com/repos/kamranahmedse/developer-roadmap/labels/topic-change",
            "name": "topic-change",
            "color": "5454FC",
            "default": false,
            "description": "Missing or deprecated topics in roadmap"
          },
          {
            "id": 6934972635,
            "node_id": "LA_kwDOBRIuNs8AAAABnVtI2w",
            "url": "https://api.github.com/repos/kamranahmedse/developer-roadmap/labels/frontend",
            "name": "frontend",
            "color": "aa009c",
            "default": false,
            "description": "Roadmap: frontend"
          }
        ],
        "state": "closed",
        "locked": false,
        "assignee": null,
        "assignees": [

        ],
        "milestone": null,
        "comments": 1,
        "created_at": "2025-09-30T03:25:31Z",
        "updated_at": "2025-10-21T09:29:22Z",
        "closed_at": "2025-10-21T09:29:22Z",
        "active_lock_reason": null,
        "sub_issues_summary": {
          "total": 0,
          "completed": 0,
          "percent_completed": 0
        },
        "issue_dependencies_summary": {
          "blocked_by": 0,
          "total_blocked_by": 0,
          "blocking": 0,
          "total_blocking": 0
        },
        "body": "### What is the URL where the issue is happening\n\nhttps://roadmap.sh/frontend\n\n### What browsers are you seeing the problem on?\n\n_No response_\n\n### Describe the Bug\n\n<img width=\"603\" height=\"864\" alt=\"Image\" src=\"https://github.com/user-attachments/assets/258cc4cc-5ba6-48d2-87d8-8df43893783d\" />\n\nContent not showing\n\n### Output from browser console (if any)\n\n_No response_\n\n### Participation\n\n- [x] I am willing to submit a pull request for this issue.",
        "reactions": {
          "url": "https://api.github.com/repos/kamranahmedse/developer-roadmap/issues/9199/reactions",
          "total_count": 0,
          "+1": 0,
          "-1": 0,
          "laugh": 0,
          "hooray": 0,
          "confused": 0,
          "heart": 0,
          "rocket": 0,
          "eyes": 0
        },
        "timeline_url": "https://api.github.com/repos/kamranahmedse/developer-roadmap/issues/9199/timeline",
        "performed_via_github_app": null,
        "state_reason": "not_planned"
      }
    },
    "public": true,
    "created_at": "2025-10-21T09:29:24Z"
  },
  {
    "id": "4154071404",
    "type": "IssuesEvent",
    "actor": {
      "id": 4921183,
      "login": "kamranahmedse",
      "display_login": "kamranahmedse",
      "gravatar_id": "",
      "url": "https://api.github.com/users/kamranahmedse",
      "avatar_url": "https://avatars.githubusercontent.com/u/4921183?"
    },
    "repo": {
      "id": 85077558,
      "name": "kamranahmedse/developer-roadmap",
      "url": "https://api.github.com/repos/kamranahmedse/developer-roadmap"
    },
    "payload": {
      "action": "closed",
      "issue": {
        "url": "https://api.github.com/repos/kamranahmedse/developer-roadmap/issues/9221",
        "repository_url": "https://api.github.com/repos/kamranahmedse/developer-roadmap",
        "labels_url": "https://api.github.com/repos/kamranahmedse/developer-roadmap/issues/9221/labels{/name}",
        "comments_url": "https://api.github.com/repos/kamranahmedse/developer-roadmap/issues/9221/comments",
        "events_url": "https://api.github.com/repos/kamranahmedse/developer-roadmap/issues/9221/events",
        "html_url": "https://github.com/kamranahmedse/developer-roadmap/issues/9221",
        "id": 3484961448,
        "node_id": "I_kwDOBRIuNs7PuEqo",
        "number": 9221,
        "title": "Lost Golang process after update",
        "user": {
          "login": "berkaykrc",
          "id": 31601800,
          "node_id": "MDQ6VXNlcjMxNjAxODAw",
          "avatar_url": "https://avatars.githubusercontent.com/u/31601800?v=4",
          "gravatar_id": "",
          "url": "https://api.github.com/users/berkaykrc",
          "html_url": "https://github.com/berkaykrc",
          "followers_url": "https://api.github.com/users/berkaykrc/followers",
          "following_url": "https://api.github.com/users/berkaykrc/following{/other_user}",
          "gists_url": "https://api.github.com/users/berkaykrc/gists{/gist_id}",
          "starred_url": "https://api.github.com/users/berkaykrc/starred{/owner}{/repo}",
          "subscriptions_url": "https://api.github.com/users/berkaykrc/subscriptions",
          "organizations_url": "https://api.github.com/users/berkaykrc/orgs",
          "repos_url": "https://api.github.com/users/berkaykrc/repos",
          "events_url": "https://api.github.com/users/berkaykrc/events{/privacy}",
          "received_events_url": "https://api.github.com/users/berkaykrc/received_events",
          "type": "User",
          "user_view_type": "public",
          "site_admin": false
        },
        "labels": [
          {
            "id": 6934955806,
            "node_id": "LA_kwDOBRIuNs8AAAABnVsHHg",
            "url": "https://api.github.com/repos/kamranahmedse/developer-roadmap/labels/topic-change",
            "name": "topic-change",
            "color": "5454FC",
            "default": false,
            "description": "Missing or deprecated topics in roadmap"
          },
          {
            "id": 6934972690,
            "node_id": "LA_kwDOBRIuNs8AAAABnVtJEg",
            "url": "https://api.github.com/repos/kamranahmedse/developer-roadmap/labels/golang",
            "name": "golang",
            "color": "372d4a",
            "default": false,
            "description": "Roadmap: golang"
          }
        ],
        "state": "closed",
        "locked": false,
        "assignee": null,
        "assignees": [

        ],
        "milestone": null,
        "comments": 1,
        "created_at": "2025-10-05T16:43:21Z",
        "updated_at": "2025-10-21T06:17:12Z",
        "closed_at": "2025-10-21T06:17:12Z",
        "active_lock_reason": null,
        "sub_issues_summary": {
          "total": 0,
          "completed": 0,
          "percent_completed": 0
        },
        "issue_dependencies_summary": {
          "blocked_by": 0,
          "total_blocked_by": 0,
          "blocking": 0,
          "total_blocking": 0
        },
        "body": "### Roadmap URL\n\nhttps://roadmap.sh/golang\n\n### Suggestions\n\nAfter Golang roadmap revamp I lost my process. After that I commented on an already opened issue instead of creating new one with comment \n\n> What about previous progress? I made a comment on the commit, but did not get a response? This issue and my question were asked 2 weeks ago.\n\nhttps://github.com/kamranahmedse/developer-roadmap/commit/76a9a62afb291c29231a05d203d8ff5cf81494af#commitcomment-162151444\n\nIt's been four months and this issue still persists. Despite being told it would be fixed, it has not been. I cannot figure out what I did or not and lots of sources missing/removed/changed. \n\nPrevious issue closed as complete. #8923 ",
        "reactions": {
          "url": "https://api.github.com/repos/kamranahmedse/developer-roadmap/issues/9221/reactions",
          "total_count": 0,
          "+1": 0,
          "-1": 0,
          "laugh": 0,
          "hooray": 0,
          "confused": 0,
          "heart": 0,
          "rocket": 0,
          "eyes": 0
        },
        "timeline_url": "https://api.github.com/repos/kamranahmedse/developer-roadmap/issues/9221/timeline",
        "performed_via_github_app": null,
        "state_reason": "not_planned"
      }
    },
    "public": true,
    "created_at": "2025-10-21T06:17:13Z"
  },
  {
    "id": "4154071308",
    "type": "IssueCommentEvent",
    "actor": {
      "id": 4921183,
      "login": "kamranahmedse",
      "display_login": "kamranahmedse",
      "gravatar_id": "",
      "url": "https://api.github.com/users/kamranahmedse",
      "avatar_url": "https://avatars.githubusercontent.com/u/4921183?"
    },
    "repo": {
      "id": 85077558,
      "name": "kamranahmedse/developer-roadmap",
      "url": "https://api.github.com/repos/kamranahmedse/developer-roadmap"
    },
    "payload": {
      "action": "created",
      "issue": {
        "url": "https://api.github.com/repos/kamranahmedse/developer-roadmap/issues/9221",
        "repository_url": "https://api.github.com/repos/kamranahmedse/developer-roadmap",
        "labels_url": "https://api.github.com/repos/kamranahmedse/developer-roadmap/issues/9221/labels{/name}",
        "comments_url": "https://api.github.com/repos/kamranahmedse/developer-roadmap/issues/9221/comments",
        "events_url": "https://api.github.com/repos/kamranahmedse/developer-roadmap/issues/9221/events",
        "html_url": "https://github.com/kamranahmedse/developer-roadmap/issues/9221",
        "id": 3484961448,
        "node_id": "I_kwDOBRIuNs7PuEqo",
        "number": 9221,
        "title": "Lost Golang process after update",
        "user": {
          "login": "berkaykrc",
          "id": 31601800,
          "node_id": "MDQ6VXNlcjMxNjAxODAw",
          "avatar_url": "https://avatars.githubusercontent.com/u/31601800?v=4",
          "gravatar_id": "",
          "url": "https://api.github.com/users/berkaykrc",
          "html_url": "https://github.com/berkaykrc",
          "followers_url": "https://api.github.com/users/berkaykrc/followers",
          "following_url": "https://api.github.com/users/berkaykrc/following{/other_user}",
          "gists_url": "https://api.github.com/users/berkaykrc/gists{/gist_id}",
          "starred_url": "https://api.github.com/users/berkaykrc/starred{/owner}{/repo}",
          "subscriptions_url": "https://api.github.com/users/berkaykrc/subscriptions",
          "organizations_url": "https://api.github.com/users/berkaykrc/orgs",
          "repos_url": "https://api.github.com/users/berkaykrc/repos",
          "events_url": "https://api.github.com/users/berkaykrc/events{/privacy}",
          "received_events_url": "https://api.github.com/users/berkaykrc/received_events",
          "type": "User",
          "user_view_type": "public",
          "site_admin": false
        },
        "labels": [
          {
            "id": 6934955806,
            "node_id": "LA_kwDOBRIuNs8AAAABnVsHHg",
            "url": "https://api.github.com/repos/kamranahmedse/developer-roadmap/labels/topic-change",
            "name": "topic-change",
            "color": "5454FC",
            "default": false,
            "description": "Missing or deprecated topics in roadmap"
          },
          {
            "id": 6934972690,
            "node_id": "LA_kwDOBRIuNs8AAAABnVtJEg",
            "url": "https://api.github.com/repos/kamranahmedse/developer-roadmap/labels/golang",
            "name": "golang",
            "color": "372d4a",
            "default": false,
            "description": "Roadmap: golang"
          }
        ],
        "state": "closed",
        "locked": false,
        "assignee": null,
        "assignees": [

        ],
        "milestone": null,
        "comments": 1,
        "created_at": "2025-10-05T16:43:21Z",
        "updated_at": "2025-10-21T06:17:12Z",
        "closed_at": "2025-10-21T06:17:12Z",
        "active_lock_reason": null,
        "sub_issues_summary": {
          "total": 0,
          "completed": 0,
          "percent_completed": 0
        },
        "issue_dependencies_summary": {
          "blocked_by": 0,
          "total_blocked_by": 0,
          "blocking": 0,
          "total_blocking": 0
        },
        "body": "### Roadmap URL\n\nhttps://roadmap.sh/golang\n\n### Suggestions\n\nAfter Golang roadmap revamp I lost my process. After that I commented on an already opened issue instead of creating new one with comment \n\n> What about previous progress? I made a comment on the commit, but did not get a response? This issue and my question were asked 2 weeks ago.\n\nhttps://github.com/kamranahmedse/developer-roadmap/commit/76a9a62afb291c29231a05d203d8ff5cf81494af#commitcomment-162151444\n\nIt's been four months and this issue still persists. Despite being told it would be fixed, it has not been. I cannot figure out what I did or not and lots of sources missing/removed/changed. \n\nPrevious issue closed as complete. #8923 ",
        "reactions": {
          "url": "https://api.github.com/repos/kamranahmedse/developer-roadmap/issues/9221/reactions",
          "total_count": 0,
          "+1": 0,
          "-1": 0,
          "laugh": 0,
          "hooray": 0,
          "confused": 0,
          "heart": 0,
          "rocket": 0,
          "eyes": 0
        },
        "timeline_url": "https://api.github.com/repos/kamranahmedse/developer-roadmap/issues/9221/timeline",
        "performed_via_github_app": null,
        "state_reason": "not_planned"
      },
      "comment": {
        "url": "https://api.github.com/repos/kamranahmedse/developer-roadmap/issues/comments/3424876078",
        "html_url": "https://github.com/kamranahmedse/developer-roadmap/issues/9221#issuecomment-3424876078",
        "issue_url": "https://api.github.com/repos/kamranahmedse/developer-roadmap/issues/9221",
        "id": 3424876078,
        "node_id": "IC_kwDOBRIuNs7MI3Yu",
        "user": {
          "login": "kamranahmedse",
          "id": 4921183,
          "node_id": "MDQ6VXNlcjQ5MjExODM=",
          "avatar_url": "https://avatars.githubusercontent.com/u/4921183?v=4",
          "gravatar_id": "",
          "url": "https://api.github.com/users/kamranahmedse",
          "html_url": "https://github.com/kamranahmedse",
          "followers_url": "https://api.github.com/users/kamranahmedse/followers",
          "following_url": "https://api.github.com/users/kamranahmedse/following{/other_user}",
          "gists_url": "https://api.github.com/users/kamranahmedse/gists{/gist_id}",
          "starred_url": "https://api.github.com/users/kamranahmedse/starred{/owner}{/repo}",
          "subscriptions_url": "https://api.github.com/users/kamranahmedse/subscriptions",
          "organizations_url": "https://api.github.com/users/kamranahmedse/orgs",
          "repos_url": "https://api.github.com/users/kamranahmedse/repos",
          "events_url": "https://api.github.com/users/kamranahmedse/events{/privacy}",
          "received_events_url": "https://api.github.com/users/kamranahmedse/received_events",
          "type": "User",
          "user_view_type": "public",
          "site_admin": false
        },
        "created_at": "2025-10-21T06:17:12Z",
        "updated_at": "2025-10-21T06:17:12Z",
        "body": "Go roadmap was completely revamped so we had to get rid of the old progresses unfortunately.",
        "reactions": {
          "url": "https://api.github.com/repos/kamranahmedse/developer-roadmap/issues/comments/3424876078/reactions",
          "total_count": 0,
          "+1": 0,
          "-1": 0,
          "laugh": 0,
          "hooray": 0,
          "confused": 0,
          "heart": 0,
          "rocket": 0,
          "eyes": 0
        },
        "performed_via_github_app": null
      }
    },
    "public": true,
    "created_at": "2025-10-21T06:17:12Z"
  },
  {
    "id": "4154035180",
    "type": "IssueCommentEvent",
    "actor": {
      "id": 4921183,
      "login": "kamranahmedse",
      "display_login": "kamranahmedse",
      "gravatar_id": "",
      "url": "https://api.github.com/users/kamranahmedse",
      "avatar_url": "https://avatars.githubusercontent.com/u/4921183?"
    },
    "repo": {
      "id": 85077558,
      "name": "kamranahmedse/developer-roadmap",
      "url": "https://api.github.com/repos/kamranahmedse/developer-roadmap"
    },
    "payload": {
      "action": "created",
      "issue": {
        "url": "https://api.github.com/repos/kamranahmedse/developer-roadmap/issues/9231",
        "repository_url": "https://api.github.com/repos/kamranahmedse/developer-roadmap",
        "labels_url": "https://api.github.com/repos/kamranahmedse/developer-roadmap/issues/9231/labels{/name}",
        "comments_url": "https://api.github.com/repos/kamranahmedse/developer-roadmap/issues/9231/comments",
        "events_url": "https://api.github.com/repos/kamranahmedse/developer-roadmap/issues/9231/events",
        "html_url": "https://github.com/kamranahmedse/developer-roadmap/issues/9231",
        "id": 3494400792,
        "node_id": "I_kwDOBRIuNs7QSFMY",
        "number": 9231,
        "title": "Make Roadmaps' DevOps Projects Instantly Hands-On with KodeKloud Free Labs",
        "user": {
          "login": "nimeshmora",
          "id": 7818133,
          "node_id": "MDQ6VXNlcjc4MTgxMzM=",
          "avatar_url": "https://avatars.githubusercontent.com/u/7818133?v=4",
          "gravatar_id": "",
          "url": "https://api.github.com/users/nimeshmora",
          "html_url": "https://github.com/nimeshmora",
          "followers_url": "https://api.github.com/users/nimeshmora/followers",
          "following_url": "https://api.github.com/users/nimeshmora/following{/other_user}",
          "gists_url": "https://api.github.com/users/nimeshmora/gists{/gist_id}",
          "starred_url": "https://api.github.com/users/nimeshmora/starred{/owner}{/repo}",
          "subscriptions_url": "https://api.github.com/users/nimeshmora/subscriptions",
          "organizations_url": "https://api.github.com/users/nimeshmora/orgs",
          "repos_url": "https://api.github.com/users/nimeshmora/repos",
          "events_url": "https://api.github.com/users/nimeshmora/events{/privacy}",
          "received_events_url": "https://api.github.com/users/nimeshmora/received_events",
          "type": "User",
          "user_view_type": "public",
          "site_admin": false
        },
        "labels": [
          {
            "id": 5069765299,
            "node_id": "LA_kwDOBRIuNs8AAAABLi56sw",
            "url": "https://api.github.com/repos/kamranahmedse/developer-roadmap/labels/feature%20request",
            "name": "feature request",
            "color": "D649A4",
            "default": false,
            "description": "Indicates new feature requests"
          }
        ],
        "state": "closed",
        "locked": false,
        "assignee": null,
        "assignees": [

        ],
        "milestone": null,
        "comments": 9,
        "created_at": "2025-10-08T08:25:53Z",
        "updated_at": "2025-10-21T06:17:26Z",
        "closed_at": "2025-10-21T06:14:39Z",
        "active_lock_reason": null,
        "sub_issues_summary": {
          "total": 0,
          "completed": 0,
          "percent_completed": 0
        },
        "issue_dependencies_summary": {
          "blocked_by": 0,
          "total_blocked_by": 0,
          "blocking": 0,
          "total_blocking": 0
        },
        "body": "### Feature Description\n\n**Problem I See...**\n\nLearners want to practice end-to-end DevOps projects but struggle with local setup (OS differences, tooling versions, cloud costs). This slows progress and reduces completion rates.\n\nI am specifically talking about Roadmap's DevOps Projects here : https://roadmap.sh/devops/projects \n\n**Goal**\n\nUse KodeKloud's large Portfolio of Free Labs as the default execution environment for Roadmaps 'DevOps' Projects, so learners can:\n\n- Run projects instantly (no heavy local setups).\n- Practice with real tools (Docker, K8s, Terraform, Ansible, CI/CD, Linux, etc).\n- Follow a consistent, tested workflow directly in the browser.\n\n**Approach (V1)**\n\n1. Map Projects → Labs\n\n- For each roadmap project, link the exact KodeKloud lab(s) that cover the required tool/step.\n- Provide a step-by-step “Use This Lab” path inside each project README.\n\n2. One-Click Start\n\n- Add a “Run in KodeKloud” button (link) in project READMEs.\n- Include prerequisites, expected time, and outcomes.\n\n3. Minimal Local Setup\n\n- Keep a local path optional. Default path = KodeKloud labs.\n\n4. Artifacts\n\n- Learners export/commit artifacts (configs, manifests, pipelines) back to this repo via templates.\n\n**Scope (Initial Project Set)**\n\n- Project A: Containerize a Node/Go app → push to registry → deploy to K8s\n   _Labs: Docker basics, Kubernetes basics, kubectl, deployments_\n\n- Project B: CI/CD pipeline (build, test, scan, deploy)\n   _Labs: Git, Jenkins/GitHub Actions basics, image scanning_\n\n- Project C: Infra as Code on cloud sandbox\n   Labs: Terraform basics, provisioning workflow\n\n- Project D: Configuration management for a web stack\n   Labs: Ansible basics, playbooks, handlers, roles\n\n- Project E: Observability starter\n   Labs: Linux basics, logs, basic monitoring concepts\n\nWe’ll expand mapping in follow-ups.\n\n**Success Criteria / Metrics**\n\n- 80%+ of steps runnable without local installs.\n- 50%+ increase in project completion (self-reported or repo submissions).\n- Time-to-first-successful-run < 10 minutes.\n- ≥ 5 community PRs adding or improving lab mappings in first month.\n\n\nThis is just an initial idea — would love to hear everyone’s thoughts!",
        "reactions": {
          "url": "https://api.github.com/repos/kamranahmedse/developer-roadmap/issues/9231/reactions",
          "total_count": 0,
          "+1": 0,
          "-1": 0,
          "laugh": 0,
          "hooray": 0,
          "confused": 0,
          "heart": 0,
          "rocket": 0,
          "eyes": 0
        },
        "timeline_url": "https://api.github.com/repos/kamranahmedse/developer-roadmap/issues/9231/timeline",
        "performed_via_github_app": null,
        "state_reason": "not_planned"
      },
      "comment": {
        "url": "https://api.github.com/repos/kamranahmedse/developer-roadmap/issues/comments/3424868575",
        "html_url": "https://github.com/kamranahmedse/developer-roadmap/issues/9231#issuecomment-3424868575",
        "issue_url": "https://api.github.com/repos/kamranahmedse/developer-roadmap/issues/9231",
        "id": 3424868575,
        "node_id": "IC_kwDOBRIuNs7MI1jf",
        "user": {
          "login": "kamranahmedse",
          "id": 4921183,
          "node_id": "MDQ6VXNlcjQ5MjExODM=",
          "avatar_url": "https://avatars.githubusercontent.com/u/4921183?v=4",
          "gravatar_id": "",
          "url": "https://api.github.com/users/kamranahmedse",
          "html_url": "https://github.com/kamranahmedse",
          "followers_url": "https://api.github.com/users/kamranahmedse/followers",
          "following_url": "https://api.github.com/users/kamranahmedse/following{/other_user}",
          "gists_url": "https://api.github.com/users/kamranahmedse/gists{/gist_id}",
          "starred_url": "https://api.github.com/users/kamranahmedse/starred{/owner}{/repo}",
          "subscriptions_url": "https://api.github.com/users/kamranahmedse/subscriptions",
          "organizations_url": "https://api.github.com/users/kamranahmedse/orgs",
          "repos_url": "https://api.github.com/users/kamranahmedse/repos",
          "events_url": "https://api.github.com/users/kamranahmedse/events{/privacy}",
          "received_events_url": "https://api.github.com/users/kamranahmedse/received_events",
          "type": "User",
          "user_view_type": "public",
          "site_admin": false
        },
        "created_at": "2025-10-21T06:14:39Z",
        "updated_at": "2025-10-21T06:14:39Z",
        "body": "Thanks for the idea! We're not planning to add third-party labs right now, so closing this one. Appreciate the detailed write-up though!",
        "reactions": {
          "url": "https://api.github.com/repos/kamranahmedse/developer-roadmap/issues/comments/3424868575/reactions",
          "total_count": 1,
          "+1": 1,
          "-1": 0,
          "laugh": 0,
          "hooray": 0,
          "confused": 0,
          "heart": 0,
          "rocket": 0,
          "eyes": 0
        },
        "performed_via_github_app": null
      }
    },
    "public": true,
    "created_at": "2025-10-21T06:14:39Z"
  },
  {
    "id": "4154034992",
    "type": "IssuesEvent",
    "actor": {
      "id": 4921183,
      "login": "kamranahmedse",
      "display_login": "kamranahmedse",
      "gravatar_id": "",
      "url": "https://api.github.com/users/kamranahmedse",
      "avatar_url": "https://avatars.githubusercontent.com/u/4921183?"
    },
    "repo": {
      "id": 85077558,
      "name": "kamranahmedse/developer-roadmap",
      "url": "https://api.github.com/repos/kamranahmedse/developer-roadmap"
    },
    "payload": {
      "action": "closed",
      "issue": {
        "url": "https://api.github.com/repos/kamranahmedse/developer-roadmap/issues/9231",
        "repository_url": "https://api.github.com/repos/kamranahmedse/developer-roadmap",
        "labels_url": "https://api.github.com/repos/kamranahmedse/developer-roadmap/issues/9231/labels{/name}",
        "comments_url": "https://api.github.com/repos/kamranahmedse/developer-roadmap/issues/9231/comments",
        "events_url": "https://api.github.com/repos/kamranahmedse/developer-roadmap/issues/9231/events",
        "html_url": "https://github.com/kamranahmedse/developer-roadmap/issues/9231",
        "id": 3494400792,
        "node_id": "I_kwDOBRIuNs7QSFMY",
        "number": 9231,
        "title": "Make Roadmaps' DevOps Projects Instantly Hands-On with KodeKloud Free Labs",
        "user": {
          "login": "nimeshmora",
          "id": 7818133,
          "node_id": "MDQ6VXNlcjc4MTgxMzM=",
          "avatar_url": "https://avatars.githubusercontent.com/u/7818133?v=4",
          "gravatar_id": "",
          "url": "https://api.github.com/users/nimeshmora",
          "html_url": "https://github.com/nimeshmora",
          "followers_url": "https://api.github.com/users/nimeshmora/followers",
          "following_url": "https://api.github.com/users/nimeshmora/following{/other_user}",
          "gists_url": "https://api.github.com/users/nimeshmora/gists{/gist_id}",
          "starred_url": "https://api.github.com/users/nimeshmora/starred{/owner}{/repo}",
          "subscriptions_url": "https://api.github.com/users/nimeshmora/subscriptions",
          "organizations_url": "https://api.github.com/users/nimeshmora/orgs",
          "repos_url": "https://api.github.com/users/nimeshmora/repos",
          "events_url": "https://api.github.com/users/nimeshmora/events{/privacy}",
          "received_events_url": "https://api.github.com/users/nimeshmora/received_events",
          "type": "User",
          "user_view_type": "public",
          "site_admin": false
        },
        "labels": [
          {
            "id": 5069765299,
            "node_id": "LA_kwDOBRIuNs8AAAABLi56sw",
            "url": "https://api.github.com/repos/kamranahmedse/developer-roadmap/labels/feature%20request",
            "name": "feature request",
            "color": "D649A4",
            "default": false,
            "description": "Indicates new feature requests"
          }
        ],
        "state": "closed",
        "locked": false,
        "assignee": null,
        "assignees": [

        ],
        "milestone": null,
        "comments": 9,
        "created_at": "2025-10-08T08:25:53Z",
        "updated_at": "2025-10-21T06:17:26Z",
        "closed_at": "2025-10-21T06:14:39Z",
        "active_lock_reason": null,
        "sub_issues_summary": {
          "total": 0,
          "completed": 0,
          "percent_completed": 0
        },
        "issue_dependencies_summary": {
          "blocked_by": 0,
          "total_blocked_by": 0,
          "blocking": 0,
          "total_blocking": 0
        },
        "body": "### Feature Description\n\n**Problem I See...**\n\nLearners want to practice end-to-end DevOps projects but struggle with local setup (OS differences, tooling versions, cloud costs). This slows progress and reduces completion rates.\n\nI am specifically talking about Roadmap's DevOps Projects here : https://roadmap.sh/devops/projects \n\n**Goal**\n\nUse KodeKloud's large Portfolio of Free Labs as the default execution environment for Roadmaps 'DevOps' Projects, so learners can:\n\n- Run projects instantly (no heavy local setups).\n- Practice with real tools (Docker, K8s, Terraform, Ansible, CI/CD, Linux, etc).\n- Follow a consistent, tested workflow directly in the browser.\n\n**Approach (V1)**\n\n1. Map Projects → Labs\n\n- For each roadmap project, link the exact KodeKloud lab(s) that cover the required tool/step.\n- Provide a step-by-step “Use This Lab” path inside each project README.\n\n2. One-Click Start\n\n- Add a “Run in KodeKloud” button (link) in project READMEs.\n- Include prerequisites, expected time, and outcomes.\n\n3. Minimal Local Setup\n\n- Keep a local path optional. Default path = KodeKloud labs.\n\n4. Artifacts\n\n- Learners export/commit artifacts (configs, manifests, pipelines) back to this repo via templates.\n\n**Scope (Initial Project Set)**\n\n- Project A: Containerize a Node/Go app → push to registry → deploy to K8s\n   _Labs: Docker basics, Kubernetes basics, kubectl, deployments_\n\n- Project B: CI/CD pipeline (build, test, scan, deploy)\n   _Labs: Git, Jenkins/GitHub Actions basics, image scanning_\n\n- Project C: Infra as Code on cloud sandbox\n   Labs: Terraform basics, provisioning workflow\n\n- Project D: Configuration management for a web stack\n   Labs: Ansible basics, playbooks, handlers, roles\n\n- Project E: Observability starter\n   Labs: Linux basics, logs, basic monitoring concepts\n\nWe’ll expand mapping in follow-ups.\n\n**Success Criteria / Metrics**\n\n- 80%+ of steps runnable without local installs.\n- 50%+ increase in project completion (self-reported or repo submissions).\n- Time-to-first-successful-run < 10 minutes.\n- ≥ 5 community PRs adding or improving lab mappings in first month.\n\n\nThis is just an initial idea — would love to hear everyone’s thoughts!",
        "reactions": {
          "url": "https://api.github.com/repos/kamranahmedse/developer-roadmap/issues/9231/reactions",
          "total_count": 0,
          "+1": 0,
          "-1": 0,
          "laugh": 0,
          "hooray": 0,
          "confused": 0,
          "heart": 0,
          "rocket": 0,
          "eyes": 0
        },
        "timeline_url": "https://api.github.com/repos/kamranahmedse/developer-roadmap/issues/9231/timeline",
        "performed_via_github_app": null,
        "state_reason": "not_planned"
      }
    },
    "public": true,
    "created_at": "2025-10-21T06:14:40Z"
  },
  {
    "id": "5332425151",
    "type": "PushEvent",
    "actor": {
      "id": 4921183,
      "login": "kamranahmedse",
      "display_login": "kamranahmedse",
      "gravatar_id": "",
      "url": "https://api.github.com/users/kamranahmedse",
      "avatar_url": "https://avatars.githubusercontent.com/u/4921183?"
    },
    "repo": {
      "id": 85077558,
      "name": "kamranahmedse/developer-roadmap",
      "url": "https://api.github.com/repos/kamranahmedse/developer-roadmap"
    },
    "payload": {
      "repository_id": 85077558,
      "push_id": 27622156145,
      "ref": "refs/heads/master",
      "head": "1a83102edd3539b572e97222114aae80452830ed",
      "before": "8a54454b217887e7c6a3972760aa0922d4afd946"
    },
    "public": true,
    "created_at": "2025-10-20T13:57:03Z"
  },
  {
    "id": "4138711690",
    "type": "IssueCommentEvent",
    "actor": {
      "id": 4921183,
      "login": "kamranahmedse",
      "display_login": "kamranahmedse",
      "gravatar_id": "",
      "url": "https://api.github.com/users/kamranahmedse",
      "avatar_url": "https://avatars.githubusercontent.com/u/4921183?"
    },
    "repo": {
      "id": 85077558,
      "name": "kamranahmedse/developer-roadmap",
      "url": "https://api.github.com/repos/kamranahmedse/developer-roadmap"
    },
    "payload": {
      "action": "created",
      "issue": {
        "url": "https://api.github.com/repos/kamranahmedse/developer-roadmap/issues/9220",
        "repository_url": "https://api.github.com/repos/kamranahmedse/developer-roadmap",
        "labels_url": "https://api.github.com/repos/kamranahmedse/developer-roadmap/issues/9220/labels{/name}",
        "comments_url": "https://api.github.com/repos/kamranahmedse/developer-roadmap/issues/9220/comments",
        "events_url": "https://api.github.com/repos/kamranahmedse/developer-roadmap/issues/9220/events",
        "html_url": "https://github.com/kamranahmedse/developer-roadmap/pull/9220",
        "id": 3484758757,
        "node_id": "PR_kwDOBRIuNs6sJCMz",
        "number": 9220,
        "title": "enhance performance phase 1 ",
        "user": {
          "login": "abdo-spices",
          "id": 93441520,
          "node_id": "U_kgDOBZHN8A",
          "avatar_url": "https://avatars.githubusercontent.com/u/93441520?v=4",
          "gravatar_id": "",
          "url": "https://api.github.com/users/abdo-spices",
          "html_url": "https://github.com/abdo-spices",
          "followers_url": "https://api.github.com/users/abdo-spices/followers",
          "following_url": "https://api.github.com/users/abdo-spices/following{/other_user}",
          "gists_url": "https://api.github.com/users/abdo-spices/gists{/gist_id}",
          "starred_url": "https://api.github.com/users/abdo-spices/starred{/owner}{/repo}",
          "subscriptions_url": "https://api.github.com/users/abdo-spices/subscriptions",
          "organizations_url": "https://api.github.com/users/abdo-spices/orgs",
          "repos_url": "https://api.github.com/users/abdo-spices/repos",
          "events_url": "https://api.github.com/users/abdo-spices/events{/privacy}",
          "received_events_url": "https://api.github.com/users/abdo-spices/received_events",
          "type": "User",
          "user_view_type": "public",
          "site_admin": false
        },
        "labels": [

        ],
        "state": "closed",
        "locked": false,
        "assignee": null,
        "assignees": [

        ],
        "milestone": null,
        "comments": 1,
        "created_at": "2025-10-05T12:21:46Z",
        "updated_at": "2025-10-20T13:40:56Z",
        "closed_at": "2025-10-20T13:40:56Z",
        "active_lock_reason": null,
        "draft": false,
        "pull_request": {
          "url": "https://api.github.com/repos/kamranahmedse/developer-roadmap/pulls/9220",
          "html_url": "https://github.com/kamranahmedse/developer-roadmap/pull/9220",
          "diff_url": "https://github.com/kamranahmedse/developer-roadmap/pull/9220.diff",
          "patch_url": "https://github.com/kamranahmedse/developer-roadmap/pull/9220.patch",
          "merged_at": null
        },
        "body": "### before:\r\n<img width=\"746\" height=\"629\" alt=\"image\" src=\"https://github.com/user-attachments/assets/5ad9a577-aedf-4f74-8814-799cc6588d2f\" />\r\n\r\n### after: \r\n<img width=\"740\" height=\"822\" alt=\"image\" src=\"https://github.com/user-attachments/assets/d7c0f178-5311-4457-a33f-0f0515a748f8\" />",
        "reactions": {
          "url": "https://api.github.com/repos/kamranahmedse/developer-roadmap/issues/9220/reactions",
          "total_count": 0,
          "+1": 0,
          "-1": 0,
          "laugh": 0,
          "hooray": 0,
          "confused": 0,
          "heart": 0,
          "rocket": 0,
          "eyes": 0
        },
        "timeline_url": "https://api.github.com/repos/kamranahmedse/developer-roadmap/issues/9220/timeline",
        "performed_via_github_app": null,
        "state_reason": null
      },
      "comment": {
        "url": "https://api.github.com/repos/kamranahmedse/developer-roadmap/issues/comments/3422114387",
        "html_url": "https://github.com/kamranahmedse/developer-roadmap/pull/9220#issuecomment-3422114387",
        "issue_url": "https://api.github.com/repos/kamranahmedse/developer-roadmap/issues/9220",
        "id": 3422114387,
        "node_id": "IC_kwDOBRIuNs7L-VJT",
        "user": {
          "login": "kamranahmedse",
          "id": 4921183,
          "node_id": "MDQ6VXNlcjQ5MjExODM=",
          "avatar_url": "https://avatars.githubusercontent.com/u/4921183?v=4",
          "gravatar_id": "",
          "url": "https://api.github.com/users/kamranahmedse",
          "html_url": "https://github.com/kamranahmedse",
          "followers_url": "https://api.github.com/users/kamranahmedse/followers",
          "following_url": "https://api.github.com/users/kamranahmedse/following{/other_user}",
          "gists_url": "https://api.github.com/users/kamranahmedse/gists{/gist_id}",
          "starred_url": "https://api.github.com/users/kamranahmedse/starred{/owner}{/repo}",
          "subscriptions_url": "https://api.github.com/users/kamranahmedse/subscriptions",
          "organizations_url": "https://api.github.com/users/kamranahmedse/orgs",
          "repos_url": "https://api.github.com/users/kamranahmedse/repos",
          "events_url": "https://api.github.com/users/kamranahmedse/events{/privacy}",
          "received_events_url": "https://api.github.com/users/kamranahmedse/received_events",
          "type": "User",
          "user_view_type": "public",
          "site_admin": false
        },
        "created_at": "2025-10-20T13:40:56Z",
        "updated_at": "2025-10-20T13:40:56Z",
        "body": "Thanks for the PR! We’re in the middle of a full refactor of this area, so the patch will be obsolete shortly. Rather than putting it through review and testing now, we'll fold the ideas into the new implementation.",
        "reactions": {
          "url": "https://api.github.com/repos/kamranahmedse/developer-roadmap/issues/comments/3422114387/reactions",
          "total_count": 0,
          "+1": 0,
          "-1": 0,
          "laugh": 0,
          "hooray": 0,
          "confused": 0,
          "heart": 0,
          "rocket": 0,
          "eyes": 0
        },
        "performed_via_github_app": null
      }
    },
    "public": true,
    "created_at": "2025-10-20T13:40:56Z"
  },
  {
    "id": "4138711459",
    "type": "PullRequestEvent",
    "actor": {
      "id": 4921183,
      "login": "kamranahmedse",
      "display_login": "kamranahmedse",
      "gravatar_id": "",
      "url": "https://api.github.com/users/kamranahmedse",
      "avatar_url": "https://avatars.githubusercontent.com/u/4921183?"
    },
    "repo": {
      "id": 85077558,
      "name": "kamranahmedse/developer-roadmap",
      "url": "https://api.github.com/repos/kamranahmedse/developer-roadmap"
    },
    "payload": {
      "action": "closed",
      "number": 9220,
      "pull_request": {
        "url": "https://api.github.com/repos/kamranahmedse/developer-roadmap/pulls/9220",
        "id": 2888049459,
        "number": 9220,
        "head": {
          "ref": "refactor/performance",
          "sha": "9350975b2b311bea6987b1fc6724bbd3cb64865b",
          "repo": {
            "id": 1068371165,
            "url": "https://api.github.com/repos/abdo-spices/developer-roadmap",
            "name": "developer-roadmap"
          }
        },
        "base": {
          "ref": "master",
          "sha": "8247f19850d11874e2f6e03ebe0b789ea6754806",
          "repo": {
            "id": 85077558,
            "url": "https://api.github.com/repos/kamranahmedse/developer-roadmap",
            "name": "developer-roadmap"
          }
        }
      }
    },
    "public": true,
    "created_at": "2025-10-05T18:53:48Z"
  },
  {
    "id": "5331967560",
    "type": "PushEvent",
    "actor": {
      "id": 4921183,
      "login": "kamranahmedse",
      "display_login": "kamranahmedse",
      "gravatar_id": "",
      "url": "https://api.github.com/users/kamranahmedse",
      "avatar_url": "https://avatars.githubusercontent.com/u/4921183?"
    },
    "repo": {
      "id": 85077558,
      "name": "kamranahmedse/developer-roadmap",
      "url": "https://api.github.com/repos/kamranahmedse/developer-roadmap"
    },
    "payload": {
      "repository_id": 85077558,
      "push_id": 27621694867,
      "ref": "refs/heads/master",
      "head": "8a54454b217887e7c6a3972760aa0922d4afd946",
      "before": "37d4d78d1f785c938a540b8042e86d4ee41f4439"
    },
    "public": true,
    "created_at": "2025-10-20T13:38:00Z"
  },
  {
    "id": "5324915152",
    "type": "PushEvent",
    "actor": {
      "id": 4921183,
      "login": "kamranahmedse",
      "display_login": "kamranahmedse",
      "gravatar_id": "",
      "url": "https://api.github.com/users/kamranahmedse",
      "avatar_url": "https://avatars.githubusercontent.com/u/4921183?"
    },
    "repo": {
      "id": 85077558,
      "name": "kamranahmedse/developer-roadmap",
      "url": "https://api.github.com/repos/kamranahmedse/developer-roadmap"
    },
    "payload": {
      "repository_id": 85077558,
      "push_id": 27614595661,
      "ref": "refs/heads/master",
      "head": "37d4d78d1f785c938a540b8042e86d4ee41f4439",
      "before": "64798ee5a6fbb60370148a4230549b0bd0bc77b0"
    },
    "public": true,
    "created_at": "2025-10-20T07:39:35Z"
  },
  {
    "id": "5324903667",
    "type": "PushEvent",
    "actor": {
      "id": 4921183,
      "login": "kamranahmedse",
      "display_login": "kamranahmedse",
      "gravatar_id": "",
      "url": "https://api.github.com/users/kamranahmedse",
      "avatar_url": "https://avatars.githubusercontent.com/u/4921183?"
    },
    "repo": {
      "id": 1054440052,
      "name": "joao4xz/developer-roadmap",
      "url": "https://api.github.com/repos/joao4xz/developer-roadmap"
    },
    "payload": {
      "repository_id": 1054440052,
      "push_id": 27614584112,
      "ref": "refs/heads/fix/undefined-pandas-title",
      "head": "e0c8c4382f0547e218ec576442e90f09d9f41e04",
      "before": "d1d641dc3c68c60cfe754a746b182ab1605ab84f"
    },
    "public": true,
    "created_at": "2025-10-20T07:38:56Z"
  },
  {
    "id": "5324895396",
    "type": "PushEvent",
    "actor": {
      "id": 4921183,
      "login": "kamranahmedse",
      "display_login": "kamranahmedse",
      "gravatar_id": "",
      "url": "https://api.github.com/users/kamranahmedse",
      "avatar_url": "https://avatars.githubusercontent.com/u/4921183?"
    },
    "repo": {
      "id": 85077558,
      "name": "kamranahmedse/developer-roadmap",
      "url": "https://api.github.com/repos/kamranahmedse/developer-roadmap"
    },
    "payload": {
      "repository_id": 85077558,
      "push_id": 27614575878,
      "ref": "refs/heads/master",
      "head": "64798ee5a6fbb60370148a4230549b0bd0bc77b0",
      "before": "cd838c24853d02b7dc505520d54b8a91ec8b050c"
    },
    "public": true,
    "created_at": "2025-10-20T07:38:27Z"
  },
  {
    "id": "5324891656",
    "type": "PushEvent",
    "actor": {
      "id": 4921183,
      "login": "kamranahmedse",
      "display_login": "kamranahmedse",
      "gravatar_id": "",
      "url": "https://api.github.com/users/kamranahmedse",
      "avatar_url": "https://avatars.githubusercontent.com/u/4921183?"
    },
    "repo": {
      "id": 1054995286,
      "name": "AhmedIbrahimSH/developer-roadmap",
      "url": "https://api.github.com/repos/AhmedIbrahimSH/developer-roadmap"
    },
    "payload": {
      "repository_id": 1054995286,
      "push_id": 27614572094,
      "ref": "refs/heads/patch-1",
      "head": "29638f496e2bcd1ecf58cc440776044e44c2f127",
      "before": "a26f68fec41fd0d9995e1fe6679464d4619be1bd"
    },
    "public": true,
    "created_at": "2025-10-20T07:38:14Z"
  },
  {
    "id": "4131668064",
    "type": "PullRequestEvent",
    "actor": {
      "id": 4921183,
      "login": "kamranahmedse",
      "display_login": "kamranahmedse",
      "gravatar_id": "",
      "url": "https://api.github.com/users/kamranahmedse",
      "avatar_url": "https://avatars.githubusercontent.com/u/4921183?"
    },
    "repo": {
      "id": 85077558,
      "name": "kamranahmedse/developer-roadmap",
      "url": "https://api.github.com/repos/kamranahmedse/developer-roadmap"
    },
    "payload": {
      "action": "closed",
      "number": 9145,
      "pull_request": {
        "url": "https://api.github.com/repos/kamranahmedse/developer-roadmap/pulls/9145",
        "id": 2821957595,
        "number": 9145,
        "head": {
          "ref": "master",
          "sha": "0a727751dada5118301680c713ac06e02426ec87",
          "repo": {
            "id": 1052612247,
            "url": "https://api.github.com/repos/ArcaneCrowA/developer-roadmap",
            "name": "developer-roadmap"
          }
        },
        "base": {
          "ref": "master",
          "sha": "775ccef13f81ba253af5d127beaa841d6bf02d11",
          "repo": {
            "id": 85077558,
            "url": "https://api.github.com/repos/kamranahmedse/developer-roadmap",
            "name": "developer-roadmap"
          }
        }
      }
    },
    "public": true,
    "created_at": "2025-09-22T04:23:55Z"
  },
  {
    "id": "4131662711",
    "type": "IssuesEvent",
    "actor": {
      "id": 4921183,
      "login": "kamranahmedse",
      "display_login": "kamranahmedse",
      "gravatar_id": "",
      "url": "https://api.github.com/users/kamranahmedse",
      "avatar_url": "https://avatars.githubusercontent.com/u/4921183?"
    },
    "repo": {
      "id": 85077558,
      "name": "kamranahmedse/developer-roadmap",
      "url": "https://api.github.com/repos/kamranahmedse/developer-roadmap"
    },
    "payload": {
      "action": "closed",
      "issue": {
        "url": "https://api.github.com/repos/kamranahmedse/developer-roadmap/issues/9147",
        "repository_url": "https://api.github.com/repos/kamranahmedse/developer-roadmap",
        "labels_url": "https://api.github.com/repos/kamranahmedse/developer-roadmap/issues/9147/labels{/name}",
        "comments_url": "https://api.github.com/repos/kamranahmedse/developer-roadmap/issues/9147/comments",
        "events_url": "https://api.github.com/repos/kamranahmedse/developer-roadmap/issues/9147/events",
        "html_url": "https://github.com/kamranahmedse/developer-roadmap/issues/9147",
        "id": 3412184973,
        "node_id": "I_kwDOBRIuNs7LYc-N",
        "number": 9147,
        "title": "An article in golang/Multiple Return Values isn't free",
        "user": {
          "login": "tawfiqkhalilieh",
          "id": 87164562,
          "node_id": "MDQ6VXNlcjg3MTY0NTYy",
          "avatar_url": "https://avatars.githubusercontent.com/u/87164562?v=4",
          "gravatar_id": "",
          "url": "https://api.github.com/users/tawfiqkhalilieh",
          "html_url": "https://github.com/tawfiqkhalilieh",
          "followers_url": "https://api.github.com/users/tawfiqkhalilieh/followers",
          "following_url": "https://api.github.com/users/tawfiqkhalilieh/following{/other_user}",
          "gists_url": "https://api.github.com/users/tawfiqkhalilieh/gists{/gist_id}",
          "starred_url": "https://api.github.com/users/tawfiqkhalilieh/starred{/owner}{/repo}",
          "subscriptions_url": "https://api.github.com/users/tawfiqkhalilieh/subscriptions",
          "organizations_url": "https://api.github.com/users/tawfiqkhalilieh/orgs",
          "repos_url": "https://api.github.com/users/tawfiqkhalilieh/repos",
          "events_url": "https://api.github.com/users/tawfiqkhalilieh/events{/privacy}",
          "received_events_url": "https://api.github.com/users/tawfiqkhalilieh/received_events",
          "type": "User",
          "user_view_type": "public",
          "site_admin": false
        },
        "labels": [
          {
            "id": 6934955806,
            "node_id": "LA_kwDOBRIuNs8AAAABnVsHHg",
            "url": "https://api.github.com/repos/kamranahmedse/developer-roadmap/labels/topic-change",
            "name": "topic-change",
            "color": "5454FC",
            "default": false,
            "description": "Missing or deprecated topics in roadmap"
          },
          {
            "id": 6934972690,
            "node_id": "LA_kwDOBRIuNs8AAAABnVtJEg",
            "url": "https://api.github.com/repos/kamranahmedse/developer-roadmap/labels/golang",
            "name": "golang",
            "color": "372d4a",
            "default": false,
            "description": "Roadmap: golang"
          }
        ],
        "state": "closed",
        "locked": false,
        "assignee": null,
        "assignees": [

        ],
        "milestone": null,
        "comments": 0,
        "created_at": "2025-09-12T23:31:48Z",
        "updated_at": "2025-10-20T07:36:12Z",
        "closed_at": "2025-10-20T07:36:12Z",
        "active_lock_reason": null,
        "sub_issues_summary": {
          "total": 0,
          "completed": 0,
          "percent_completed": 0
        },
        "issue_dependencies_summary": {
          "blocked_by": 0,
          "total_blocked_by": 0,
          "blocking": 0,
          "total_blocking": 0
        },
        "body": "### What is the URL where the issue is happening\n\nhttps://roadmap.sh/golang\n\n### What browsers are you seeing the problem on?\n\nChrome\n\n### Describe the Bug\n\nFix: Removed non-free article under \"Free Resources\"\nThe section of \"Multiple Return Values\" in the Golang roadmap required medium payed subscription .\n\n<img width=\"536\" height=\"390\" alt=\"Image\" src=\"https://github.com/user-attachments/assets/4d7f195e-3496-4a6d-b46c-6a9754600752\" />\n\n<img width=\"1325\" height=\"1246\" alt=\"Image\" src=\"https://github.com/user-attachments/assets/72cd3360-c759-412b-a212-faa335dba921\" />\n\n### Output from browser console (if any)\n\n_No response_\n\n### Participation\n\n- [x] I am willing to submit a pull request for this issue.",
        "reactions": {
          "url": "https://api.github.com/repos/kamranahmedse/developer-roadmap/issues/9147/reactions",
          "total_count": 0,
          "+1": 0,
          "-1": 0,
          "laugh": 0,
          "hooray": 0,
          "confused": 0,
          "heart": 0,
          "rocket": 0,
          "eyes": 0
        },
        "timeline_url": "https://api.github.com/repos/kamranahmedse/developer-roadmap/issues/9147/timeline",
        "performed_via_github_app": null,
        "state_reason": "completed"
      }
    },
    "public": true,
    "created_at": "2025-10-20T07:36:14Z"
  },
  {
    "id": "5324854725",
    "type": "PushEvent",
    "actor": {
      "id": 4921183,
      "login": "kamranahmedse",
      "display_login": "kamranahmedse",
      "gravatar_id": "",
      "url": "https://api.github.com/users/kamranahmedse",
      "avatar_url": "https://avatars.githubusercontent.com/u/4921183?"
    },
    "repo": {
      "id": 85077558,
      "name": "kamranahmedse/developer-roadmap",
      "url": "https://api.github.com/repos/kamranahmedse/developer-roadmap"
    },
    "payload": {
      "repository_id": 85077558,
      "push_id": 27614535043,
      "ref": "refs/heads/master",
      "head": "cd838c24853d02b7dc505520d54b8a91ec8b050c",
      "before": "68d68c9a247323dbdcc2031011292e0e462e3949"
    },
    "public": true,
    "created_at": "2025-10-20T07:36:09Z"
  },
  {
    "id": "4131647164",
    "type": "PullRequestEvent",
    "actor": {
      "id": 4921183,
      "login": "kamranahmedse",
      "display_login": "kamranahmedse",
      "gravatar_id": "",
      "url": "https://api.github.com/users/kamranahmedse",
      "avatar_url": "https://avatars.githubusercontent.com/u/4921183?"
    },
    "repo": {
      "id": 85077558,
      "name": "kamranahmedse/developer-roadmap",
      "url": "https://api.github.com/repos/kamranahmedse/developer-roadmap"
    },
    "payload": {
      "action": "closed",
      "number": 9158,
      "pull_request": {
        "url": "https://api.github.com/repos/kamranahmedse/developer-roadmap/pulls/9158",
        "id": 2838379900,
        "number": 9158,
        "head": {
          "ref": "fix-changelog-navigation-hover",
          "sha": "43b4dc4708e6bd19ebd88fcbc7b67f9b053b9428",
          "repo": {
            "id": 886290208,
            "url": "https://api.github.com/repos/heyOnuoha/developer-roadmap",
            "name": "developer-roadmap"
          }
        },
        "base": {
          "ref": "master",
          "sha": "61c0cf6ac805495d8bc012f30bf5bea41feb051a",
          "repo": {
            "id": 85077558,
            "url": "https://api.github.com/repos/kamranahmedse/developer-roadmap",
            "name": "developer-roadmap"
          }
        }
      }
    },
    "public": true,
    "created_at": "2025-09-18T01:16:21Z"
  },
  {
    "id": "4131646825",
    "type": "IssueCommentEvent",
    "actor": {
      "id": 4921183,
      "login": "kamranahmedse",
      "display_login": "kamranahmedse",
      "gravatar_id": "",
      "url": "https://api.github.com/users/kamranahmedse",
      "avatar_url": "https://avatars.githubusercontent.com/u/4921183?"
    },
    "repo": {
      "id": 85077558,
      "name": "kamranahmedse/developer-roadmap",
      "url": "https://api.github.com/repos/kamranahmedse/developer-roadmap"
    },
    "payload": {
      "action": "created",
      "issue": {
        "url": "https://api.github.com/repos/kamranahmedse/developer-roadmap/issues/9158",
        "repository_url": "https://api.github.com/repos/kamranahmedse/developer-roadmap",
        "labels_url": "https://api.github.com/repos/kamranahmedse/developer-roadmap/issues/9158/labels{/name}",
        "comments_url": "https://api.github.com/repos/kamranahmedse/developer-roadmap/issues/9158/comments",
        "events_url": "https://api.github.com/repos/kamranahmedse/developer-roadmap/issues/9158/events",
        "html_url": "https://github.com/kamranahmedse/developer-roadmap/pull/9158",
        "id": 3428265128,
        "node_id": "PR_kwDOBRIuNs6pLj18",
        "number": 9158,
        "title": "chore: add functionality for changelog navigation hover and smooth scrolling",
        "user": {
          "login": "heyOnuoha",
          "id": 10455689,
          "node_id": "MDQ6VXNlcjEwNDU1Njg5",
          "avatar_url": "https://avatars.githubusercontent.com/u/10455689?v=4",
          "gravatar_id": "",
          "url": "https://api.github.com/users/heyOnuoha",
          "html_url": "https://github.com/heyOnuoha",
          "followers_url": "https://api.github.com/users/heyOnuoha/followers",
          "following_url": "https://api.github.com/users/heyOnuoha/following{/other_user}",
          "gists_url": "https://api.github.com/users/heyOnuoha/gists{/gist_id}",
          "starred_url": "https://api.github.com/users/heyOnuoha/starred{/owner}{/repo}",
          "subscriptions_url": "https://api.github.com/users/heyOnuoha/subscriptions",
          "organizations_url": "https://api.github.com/users/heyOnuoha/orgs",
          "repos_url": "https://api.github.com/users/heyOnuoha/repos",
          "events_url": "https://api.github.com/users/heyOnuoha/events{/privacy}",
          "received_events_url": "https://api.github.com/users/heyOnuoha/received_events",
          "type": "User",
          "user_view_type": "public",
          "site_admin": false
        },
        "labels": [

        ],
        "state": "closed",
        "locked": false,
        "assignee": null,
        "assignees": [

        ],
        "milestone": null,
        "comments": 1,
        "created_at": "2025-09-18T01:16:21Z",
        "updated_at": "2025-10-20T07:35:19Z",
        "closed_at": "2025-10-20T07:35:19Z",
        "active_lock_reason": null,
        "draft": false,
        "pull_request": {
          "url": "https://api.github.com/repos/kamranahmedse/developer-roadmap/pulls/9158",
          "html_url": "https://github.com/kamranahmedse/developer-roadmap/pull/9158",
          "diff_url": "https://github.com/kamranahmedse/developer-roadmap/pull/9158.diff",
          "patch_url": "https://github.com/kamranahmedse/developer-roadmap/pull/9158.patch",
          "merged_at": null
        },
        "body": "## Description\r\n\r\nImproves changelog navigation and user experience by adding hover effects and smooth scrolling to the \"Actively Maintained\" section on the homepage.\r\n\r\n## Changes Made\r\n\r\n- Enhanced hover styles for changelog items in [ChangelogBanner.astro] to match the theme's hover pattern\r\n- Added smooth scrolling behavior for changelog anchor links\r\n- Implemented JavaScript to handle proper navigation both within and to the changelog page\r\n- Added visual feedback with translate-x animation and color transitions on hover\r\n\r\n### Before\r\n\r\n![chrome-capture-2025-09-18bb](https://github.com/user-attachments/assets/d41ef8a3-0299-41a3-9bcb-c3d0838d6e97)\r\n\r\n### After\r\n![chrome-capture-2025-09-18af](https://github.com/user-attachments/assets/2ddfe12e-05eb-4ca2-8176-9b3d4e2e9c45)\r\n\r\n## Problem Solved\r\n\r\nBefore the update, the changelog items in the \"Actively Maintained\" section lacked visual feedback on hover and didn't provide smooth navigation to specific changelog entries.\r\n\r\n## Testing\r\n\r\n- [x] Tested hover effects on changelog items in \"Actively Maintained\" section\r\n- [x] Verified smooth scrolling navigation to specific changelog entries\r\n- [x] Confirmed navigation works both from homepage to changelog and within changelog page\r\n\r\n## Type of Change\r\n\r\n- [ ] Bug fix (non-breaking change which fixes an issue)\r\n- [x] New feature (non-breaking change which adds functionality)\r\n- [ ] Breaking change (fix or feature that would cause existing functionality not to work as expected)",
        "reactions": {
          "url": "https://api.github.com/repos/kamranahmedse/developer-roadmap/issues/9158/reactions",
          "total_count": 0,
          "+1": 0,
          "-1": 0,
          "laugh": 0,
          "hooray": 0,
          "confused": 0,
          "heart": 0,
          "rocket": 0,
          "eyes": 0
        },
        "timeline_url": "https://api.github.com/repos/kamranahmedse/developer-roadmap/issues/9158/timeline",
        "performed_via_github_app": null,
        "state_reason": null
      },
      "comment": {
        "url": "https://api.github.com/repos/kamranahmedse/developer-roadmap/issues/comments/3420920799",
        "html_url": "https://github.com/kamranahmedse/developer-roadmap/pull/9158#issuecomment-3420920799",
        "issue_url": "https://api.github.com/repos/kamranahmedse/developer-roadmap/issues/9158",
        "id": 3420920799,
        "node_id": "IC_kwDOBRIuNs7L5xvf",
        "user": {
          "login": "kamranahmedse",
          "id": 4921183,
          "node_id": "MDQ6VXNlcjQ5MjExODM=",
          "avatar_url": "https://avatars.githubusercontent.com/u/4921183?v=4",
          "gravatar_id": "",
          "url": "https://api.github.com/users/kamranahmedse",
          "html_url": "https://github.com/kamranahmedse",
          "followers_url": "https://api.github.com/users/kamranahmedse/followers",
          "following_url": "https://api.github.com/users/kamranahmedse/following{/other_user}",
          "gists_url": "https://api.github.com/users/kamranahmedse/gists{/gist_id}",
          "starred_url": "https://api.github.com/users/kamranahmedse/starred{/owner}{/repo}",
          "subscriptions_url": "https://api.github.com/users/kamranahmedse/subscriptions",
          "organizations_url": "https://api.github.com/users/kamranahmedse/orgs",
          "repos_url": "https://api.github.com/users/kamranahmedse/repos",
          "events_url": "https://api.github.com/users/kamranahmedse/events{/privacy}",
          "received_events_url": "https://api.github.com/users/kamranahmedse/received_events",
          "type": "User",
          "user_view_type": "public",
          "site_admin": false
        },
        "created_at": "2025-10-20T07:35:19Z",
        "updated_at": "2025-10-20T07:35:19Z",
        "body": "No need for all the JavaScript, just having the hover effect with CSS should be enough.",
        "reactions": {
          "url": "https://api.github.com/repos/kamranahmedse/developer-roadmap/issues/comments/3420920799/reactions",
          "total_count": 0,
          "+1": 0,
          "-1": 0,
          "laugh": 0,
          "hooray": 0,
          "confused": 0,
          "heart": 0,
          "rocket": 0,
          "eyes": 0
        },
        "performed_via_github_app": null
      }
    },
    "public": true,
    "created_at": "2025-10-20T07:35:19Z"
  },
  {
    "id": "5324806537",
    "type": "PushEvent",
    "actor": {
      "id": 4921183,
      "login": "kamranahmedse",
      "display_login": "kamranahmedse",
      "gravatar_id": "",
      "url": "https://api.github.com/users/kamranahmedse",
      "avatar_url": "https://avatars.githubusercontent.com/u/4921183?"
    },
    "repo": {
      "id": 85077558,
      "name": "kamranahmedse/developer-roadmap",
      "url": "https://api.github.com/repos/kamranahmedse/developer-roadmap"
    },
    "payload": {
      "repository_id": 85077558,
      "push_id": 27614486592,
      "ref": "refs/heads/master",
      "head": "68d68c9a247323dbdcc2031011292e0e462e3949",
      "before": "6b251369d34ab2c48e4e3ddbdfb8cb22c133e4d1"
    },
    "public": true,
    "created_at": "2025-10-20T07:33:24Z"
  },
  {
    "id": "5324803059",
    "type": "PushEvent",
    "actor": {
      "id": 4921183,
      "login": "kamranahmedse",
      "display_login": "kamranahmedse",
      "gravatar_id": "",
      "url": "https://api.github.com/users/kamranahmedse",
      "avatar_url": "https://avatars.githubusercontent.com/u/4921183?"
    },
    "repo": {
      "id": 1062234680,
      "name": "Dasher83/developer-roadmap",
      "url": "https://api.github.com/repos/Dasher83/developer-roadmap"
    },
    "payload": {
      "repository_id": 1062234680,
      "push_id": 27614483160,
      "ref": "refs/heads/patch-1",
      "head": "982afbbf00eb216fe2d98578ea86489780c56e47",
      "before": "6cd560a493d83fbcd55c47e5c5579307413dac0e"
    },
    "public": true,
    "created_at": "2025-10-20T07:33:12Z"
  },
  {
    "id": "5324746537",
    "type": "PushEvent",
    "actor": {
      "id": 4921183,
      "login": "kamranahmedse",
      "display_login": "kamranahmedse",
      "gravatar_id": "",
      "url": "https://api.github.com/users/kamranahmedse",
      "avatar_url": "https://avatars.githubusercontent.com/u/4921183?"
    },
    "repo": {
      "id": 85077558,
      "name": "kamranahmedse/developer-roadmap",
      "url": "https://api.github.com/repos/kamranahmedse/developer-roadmap"
    },
    "payload": {
      "repository_id": 85077558,
      "push_id": 27614425918,
      "ref": "refs/heads/master",
      "head": "6b251369d34ab2c48e4e3ddbdfb8cb22c133e4d1",
      "before": "8a0d369c69a7148e204f01ab495cc7717011e6dc"
    },
    "public": true,
    "created_at": "2025-10-20T07:30:05Z"
  },
  {
    "id": "5324733361",
    "type": "PushEvent",
    "actor": {
      "id": 4921183,
      "login": "kamranahmedse",
      "display_login": "kamranahmedse",
      "gravatar_id": "",
      "url": "https://api.github.com/users/kamranahmedse",
      "avatar_url": "https://avatars.githubusercontent.com/u/4921183?"
    },
    "repo": {
      "id": 1063083894,
      "name": "Satyaki7/developer-roadmap",
      "url": "https://api.github.com/repos/Satyaki7/developer-roadmap"
    },
    "payload": {
      "repository_id": 1063083894,
      "push_id": 27614412715,
      "ref": "refs/heads/patch-1",
      "head": "02761eeff17aac2a285ec977d001ffebdb34cfc2",
      "before": "7e5c57ce2a51601f3f1fdbde8be88f1a43b86f42"
    },
    "public": true,
    "created_at": "2025-10-20T07:29:18Z"
  },
  {
    "id": "5324701213",
    "type": "PushEvent",
    "actor": {
      "id": 4921183,
      "login": "kamranahmedse",
      "display_login": "kamranahmedse",
      "gravatar_id": "",
      "url": "https://api.github.com/users/kamranahmedse",
      "avatar_url": "https://avatars.githubusercontent.com/u/4921183?"
    },
    "repo": {
      "id": 85077558,
      "name": "kamranahmedse/developer-roadmap",
      "url": "https://api.github.com/repos/kamranahmedse/developer-roadmap"
    },
    "payload": {
      "repository_id": 85077558,
      "push_id": 27614380409,
      "ref": "refs/heads/master",
      "head": "8a0d369c69a7148e204f01ab495cc7717011e6dc",
      "before": "fb827e6118ccd16bc85d7296316c335345e1ab80"
    },
    "public": true,
    "created_at": "2025-10-20T07:27:25Z"
  },
  {
    "id": "5324560154",
    "type": "PushEvent",
    "actor": {
      "id": 4921183,
      "login": "kamranahmedse",
      "display_login": "kamranahmedse",
      "gravatar_id": "",
      "url": "https://api.github.com/users/kamranahmedse",
      "avatar_url": "https://avatars.githubusercontent.com/u/4921183?"
    },
    "repo": {
      "id": 1063439047,
      "name": "synrocka/developer-roadmap",
      "url": "https://api.github.com/repos/synrocka/developer-roadmap"
    },
    "payload": {
      "repository_id": 1063439047,
      "push_id": 27614238488,
      "ref": "refs/heads/patch-1",
      "head": "19e6c9a3b915e9c0ef0b6550078dfe3f69b7e5a5",
      "before": "0a8adc6f45186c9c3704a393a6a676f2f4838d88"
    },
    "public": true,
    "created_at": "2025-10-20T07:19:13Z"
  },
  {
    "id": "4131343408",
    "type": "PullRequestEvent",
    "actor": {
      "id": 4921183,
      "login": "kamranahmedse",
      "display_login": "kamranahmedse",
      "gravatar_id": "",
      "url": "https://api.github.com/users/kamranahmedse",
      "avatar_url": "https://avatars.githubusercontent.com/u/4921183?"
    },
    "repo": {
      "id": 85077558,
      "name": "kamranahmedse/developer-roadmap",
      "url": "https://api.github.com/repos/kamranahmedse/developer-roadmap"
    },
    "payload": {
      "action": "closed",
      "number": 9185,
      "pull_request": {
        "url": "https://api.github.com/repos/kamranahmedse/developer-roadmap/pulls/9185",
        "id": 2864752927,
        "number": 9185,
        "head": {
          "ref": "master",
          "sha": "fe2e9584c5fd920191dadf3af4a73b78cdf33fc2",
          "repo": {
            "id": 1064836001,
            "url": "https://api.github.com/repos/FenchsApps/developer-roadmap",
            "name": "developer-roadmap"
          }
        },
        "base": {
          "ref": "master",
          "sha": "9a3ec6640917e37b44f9a4709dfb6816a2e0702b",
          "repo": {
            "id": 85077558,
            "url": "https://api.github.com/repos/kamranahmedse/developer-roadmap",
            "name": "developer-roadmap"
          }
        }
      }
    },
    "public": true,
    "created_at": "2025-09-27T07:41:30Z"
  }
]
